coffe-3.0.1.dist-info/RECORD
coffe-3.0.1.dist-info/WHEEL
coffe-3.0.1.dist-info/entry_points.txt
coffe-3.0.1.dist-info/METADATA
coffe-3.0.1.dist-info/licenses/LICENSE
coffe/coffe.cpython-39-darwin.so
coffe/__init__.py
coffe/representation.py
coffe/__main__.py
