Metadata-Version: 2.1
Name: coffe
Version: 3.0.1
Summary: Python wrapper for the COrrelation Function Full-sky Estimator code
Author-Email: Goran Jelic-Cizmek <goran.jelic-cizmek@unige.ch>
License:                     GNU GENERAL PUBLIC LICENSE
Classifier: Development Status :: 4 - Beta
Classifier: Intended Audience :: Science/Research
Classifier: License :: OSI Approved
Classifier: Programming Language :: Cython
Classifier: Programming Language :: C
Classifier: Programming Language :: Python :: 3
Classifier: Programming Language :: Python :: 3.8
Classifier: Programming Language :: Python :: 3.9
Classifier: Programming Language :: Python :: 3.10
Classifier: Programming Language :: Python :: 3.11
Classifier: Programming Language :: Python :: 3.12
Classifier: Topic :: Scientific/Engineering :: Physics
Project-URL: Repository, https://github.com/JCGoran/coffe
Requires-Python: <3.13,>=3.8
Requires-Dist: numpy<2,>=1.19.5
Requires-Dist: scipy; extra == "test"
Requires-Dist: pandas; extra == "test"
Requires-Dist: pytest; extra == "test"
Requires-Dist: pdoc; extra == "docs"
Requires-Dist: pylint; extra == "dev"
Requires-Dist: mypy; extra == "dev"
Requires-Dist: isort; extra == "dev"
Requires-Dist: reorder-python-imports; extra == "dev"
Requires-Dist: autoimport; extra == "dev"
Requires-Dist: black; extra == "dev"
Requires-Dist: cibuildwheel; extra == "dev"
Requires-Dist: cmakelang; extra == "dev"
Requires-Dist: coffe[dev,docs,test]; extra == "all"
Provides-Extra: test
Provides-Extra: docs
Provides-Extra: dev
Provides-Extra: all
